flowlayer/__init__.py
flowlayer/core/__init__.py
flowlayer/core/api.py
flowlayer/core/engine.py
flowlayer/core/network.py
flowlayer/core/nodes.py
flowlayer/core/package.py
flowlayer/core/plot.py
flowlayer/core/sampler.py
flowlayer/core/stores.py
flowlayer-0.1.1.dist-info/METADATA
flowlayer-0.1.1.dist-info/WHEEL
flowlayer-0.1.1.dist-info/RECORD
