Metadata-Version: 2.1
Name: flowlayer
Version: 0.1.1
Summary: Easily build your data processing workflows.
License: BSD 3-Clause License
Author: sam
Author-email: contact@justsam.io
Requires-Python: >=3.8,<4.0
Classifier: License :: Other/Proprietary License
Classifier: Programming Language :: Python :: 3
Classifier: Programming Language :: Python :: 3.8
Classifier: Programming Language :: Python :: 3.9
Classifier: Programming Language :: Python :: 3.10
Classifier: Programming Language :: Python :: 3.11
Requires-Dist: filelock (>=3.0.12,<4.0.0)
Requires-Dist: matplotlib (>=3.3.4,<4.0.0)
Requires-Dist: networkx (>=2.5,<3.0)
Requires-Dist: numpy (>=1.20.2,<2.0.0)
Requires-Dist: pydot (>=1.4.2,<2.0.0)
Requires-Dist: semver (>=2.13.0,<3.0.0)
